pycase/__init__.py
pycase/__main__.py
pycase/case.py
pycase-0.0.3.dist-info/METADATA
pycase-0.0.3.dist-info/WHEEL
pycase-0.0.3.dist-info/entry_points.txt
pycase-0.0.3.dist-info/top_level.txt
pycase-0.0.3.dist-info/zip-safe
pycase-0.0.3.dist-info/RECORD
