Metadata-Version: 2.1
Name: pycase
Version: 0.0.3
Summary: a command line tool for camel case
Home-page: UNKNOWN
Author: Peng Shiyu
Author-email: pengshiyuyx@gmail.com
License: MIT
Keywords: pycase
Platform: UNKNOWN
